{
    "losses_distributed": [
        [
            1,
            12.1770259141922
        ],
        [
            2,
            7.461124420166016
        ],
        [
            3,
            8.497094988822937
        ],
        [
            4,
            19.898496389389038
        ],
        [
            5,
            5.130061890929937
        ],
        [
            6,
            8.493775814771652
        ],
        [
            7,
            11.579958021640778
        ],
        [
            8,
            8.475800901651382
        ],
        [
            9,
            1.8754394873976707
        ],
        [
            10,
            4.532507926225662
        ]
    ],
    "losses_centralized": [
        [
            0,
            194.37576723098755
        ],
        [
            1,
            185.93977785110474
        ],
        [
            2,
            145.8444628715515
        ],
        [
            3,
            133.8176884651184
        ],
        [
            4,
            142.4060138463974
        ],
        [
            5,
            137.13077837228775
        ],
        [
            6,
            118.87954950332642
        ],
        [
            7,
            126.52493810653687
        ],
        [
            8,
            100.86726987361908
        ],
        [
            9,
            124.12782341241837
        ],
        [
            10,
            114.51937645673752
        ]
    ],
    "fit_metrics_distributed": {
        "train_loss": [
            [
                1,
                {
                    "avg": 0.04661087887361646,
                    "all": [
                        [
                            20,
                            0.05334589593112469
                        ],
                        [
                            20,
                            0.06282766070216894
                        ],
                        [
                            20,
                            0.04710098784416914
                        ],
                        [
                            20,
                            0.04387590223923325
                        ],
                        [
                            20,
                            0.06552356500178576
                        ],
                        [
                            20,
                            0.02275806348770857
                        ],
                        [
                            20,
                            0.07684260122478008
                        ],
                        [
                            20,
                            0.018720173463225364
                        ],
                        [
                            20,
                            0.05213211290538311
                        ],
                        [
                            20,
                            0.022981825936585664
                        ]
                    ]
                }
            ],
            [
                2,
                {
                    "avg": 0.019222354255616664,
                    "all": [
                        [
                            20,
                            0.008516463870182633
                        ],
                        [
                            20,
                            0.03640144951641559
                        ],
                        [
                            20,
                            0.027723659854382278
                        ],
                        [
                            20,
                            0.009466261463239789
                        ],
                        [
                            20,
                            0.007346802309621125
                        ],
                        [
                            20,
                            0.011444307886995376
                        ],
                        [
                            20,
                            0.02236677650362253
                        ],
                        [
                            20,
                            0.011599567614030092
                        ],
                        [
                            20,
                            0.013625971018336713
                        ],
                        [
                            20,
                            0.04373228251934051
                        ]
                    ]
                }
            ],
            [
                3,
                {
                    "avg": 0.016379167812556262,
                    "all": [
                        [
                            20,
                            0.03977470584213734
                        ],
                        [
                            20,
                            0.02723627435043454
                        ],
                        [
                            20,
                            0.01533309193328023
                        ],
                        [
                            20,
                            0.006681015359936282
                        ],
                        [
                            20,
                            0.011476726771797984
                        ],
                        [
                            20,
                            0.0021621177627821455
                        ],
                        [
                            20,
                            0.0056139033462386575
                        ],
                        [
                            20,
                            0.010359674441860988
                        ],
                        [
                            20,
                            0.02017409070394933
                        ],
                        [
                            20,
                            0.024980077613145114
                        ]
                    ]
                }
            ],
            [
                4,
                {
                    "avg": 0.009366656329493708,
                    "all": [
                        [
                            20,
                            0.02436345797032118
                        ],
                        [
                            20,
                            0.0012069653781509259
                        ],
                        [
                            20,
                            0.007711900840513408
                        ],
                        [
                            20,
                            0.0009395899756782456
                        ],
                        [
                            20,
                            0.01886287140659988
                        ],
                        [
                            20,
                            0.0032239353196928276
                        ],
                        [
                            20,
                            0.002235705822931777
                        ],
                        [
                            20,
                            0.0035105807197396643
                        ],
                        [
                            20,
                            0.015651118056848646
                        ],
                        [
                            20,
                            0.015960437804460527
                        ]
                    ]
                }
            ],
            [
                5,
                {
                    "avg": 0.005742801529725057,
                    "all": [
                        [
                            20,
                            0.008073613065062091
                        ],
                        [
                            20,
                            0.012023272272199393
                        ],
                        [
                            20,
                            0.015768896648660304
                        ],
                        [
                            20,
                            0.0030372926539712353
                        ],
                        [
                            20,
                            0.005910417251288891
                        ],
                        [
                            20,
                            0.004739904624875635
                        ],
                        [
                            20,
                            0.004344872443471104
                        ],
                        [
                            20,
                            0.002427079417248024
                        ],
                        [
                            20,
                            0.0009989504022087203
                        ],
                        [
                            20,
                            0.00010371651826517337
                        ]
                    ]
                }
            ],
            [
                6,
                {
                    "avg": 0.007709595841306509,
                    "all": [
                        [
                            20,
                            0.00648902960238047
                        ],
                        [
                            20,
                            0.0020730351061502006
                        ],
                        [
                            20,
                            0.0012151563089901174
                        ],
                        [
                            20,
                            0.003841512234066613
                        ],
                        [
                            20,
                            0.004210255685029552
                        ],
                        [
                            20,
                            0.01665306743234396
                        ],
                        [
                            20,
                            0.004153953465720406
                        ],
                        [
                            20,
                            0.006046154862269759
                        ],
                        [
                            20,
                            0.02250243597663939
                        ],
                        [
                            20,
                            0.009911357739474625
                        ]
                    ]
                }
            ],
            [
                7,
                {
                    "avg": 0.00740724368917654,
                    "all": [
                        [
                            20,
                            0.01168377884896472
                        ],
                        [
                            20,
                            0.0027963344793533905
                        ],
                        [
                            20,
                            0.005322232685284689
                        ],
                        [
                            20,
                            0.0013511821069187135
                        ],
                        [
                            20,
                            0.00659920648613479
                        ],
                        [
                            20,
                            0.006010945560410619
                        ],
                        [
                            20,
                            0.004013887379551306
                        ],
                        [
                            20,
                            0.009400668612215668
                        ],
                        [
                            20,
                            0.010415217513218522
                        ],
                        [
                            20,
                            0.016478983219712973
                        ]
                    ]
                }
            ],
            [
                8,
                {
                    "avg": 0.0073344135683237255,
                    "all": [
                        [
                            20,
                            0.020157911954447626
                        ],
                        [
                            20,
                            0.007518133684061468
                        ],
                        [
                            20,
                            0.011668044643010944
                        ],
                        [
                            20,
                            0.002413235662970692
                        ],
                        [
                            20,
                            0.0005328592790647235
                        ],
                        [
                            20,
                            0.012729170499369502
                        ],
                        [
                            20,
                            0.007181878591654822
                        ],
                        [
                            20,
                            0.002934534312953474
                        ],
                        [
                            20,
                            0.00413274166676274
                        ],
                        [
                            20,
                            0.004075625388941262
                        ]
                    ]
                }
            ],
            [
                9,
                {
                    "avg": 0.005888930065253595,
                    "all": [
                        [
                            20,
                            3.488328560257159e-05
                        ],
                        [
                            20,
                            0.004806848947191611
                        ],
                        [
                            20,
                            0.00932780239963904
                        ],
                        [
                            20,
                            0.011720232432708144
                        ],
                        [
                            20,
                            0.005587961772107519
                        ],
                        [
                            20,
                            0.0008631170663647936
                        ],
                        [
                            20,
                            0.00531566692807246
                        ],
                        [
                            20,
                            0.012094849743880332
                        ],
                        [
                            20,
                            0.001274254654640572
                        ],
                        [
                            20,
                            0.007863683422328904
                        ]
                    ]
                }
            ],
            [
                10,
                {
                    "avg": 0.005175401655466203,
                    "all": [
                        [
                            20,
                            0.005975831113755703
                        ],
                        [
                            20,
                            0.009571090515237302
                        ],
                        [
                            20,
                            0.013680651085451245
                        ],
                        [
                            20,
                            0.006843751117412466
                        ],
                        [
                            20,
                            0.002756742891506292
                        ],
                        [
                            20,
                            0.0016028428237063962
                        ],
                        [
                            20,
                            0.004821910447208211
                        ],
                        [
                            20,
                            0.0036291527678258715
                        ],
                        [
                            20,
                            0.0002958541119369329
                        ],
                        [
                            20,
                            0.00257618968062161
                        ]
                    ]
                }
            ]
        ]
    },
    "eval_metrics_distributed": {
        "local_accuracy": [
            [
                1,
                {
                    "avg": 0.0,
                    "all": [
                        [
                            3,
                            0.0
                        ],
                        [
                            3,
                            0.0
                        ]
                    ]
                }
            ],
            [
                2,
                {
                    "avg": 0.39189189189189183,
                    "all": [
                        [
                            3,
                            0.25675675675675674
                        ],
                        [
                            3,
                            0.527027027027027
                        ]
                    ]
                }
            ],
            [
                3,
                {
                    "avg": 0.21522522522522522,
                    "all": [
                        [
                            3,
                            0.28378378378378377
                        ],
                        [
                            3,
                            0.14666666666666667
                        ]
                    ]
                }
            ],
            [
                4,
                {
                    "avg": 0.15333333333333332,
                    "all": [
                        [
                            3,
                            0.16
                        ],
                        [
                            3,
                            0.14666666666666667
                        ]
                    ]
                }
            ],
            [
                5,
                {
                    "avg": 0.6593693693693693,
                    "all": [
                        [
                            3,
                            0.41333333333333333
                        ],
                        [
                            3,
                            0.9054054054054054
                        ]
                    ]
                }
            ],
            [
                6,
                {
                    "avg": 0.41036036036036033,
                    "all": [
                        [
                            3,
                            0.26666666666666666
                        ],
                        [
                            3,
                            0.5540540540540541
                        ]
                    ]
                }
            ],
            [
                7,
                {
                    "avg": 0.49108108108108106,
                    "all": [
                        [
                            3,
                            0.6621621621621622
                        ],
                        [
                            3,
                            0.32
                        ]
                    ]
                }
            ],
            [
                8,
                {
                    "avg": 0.45999999999999996,
                    "all": [
                        [
                            3,
                            0.32
                        ],
                        [
                            3,
                            0.6
                        ]
                    ]
                }
            ],
            [
                9,
                {
                    "avg": 0.8716216216216216,
                    "all": [
                        [
                            3,
                            0.8783783783783784
                        ],
                        [
                            3,
                            0.8648648648648649
                        ]
                    ]
                }
            ],
            [
                10,
                {
                    "avg": 0.64,
                    "all": [
                        [
                            3,
                            0.72
                        ],
                        [
                            3,
                            0.56
                        ]
                    ]
                }
            ]
        ]
    },
    "metrics_distributed": {
        "Placeholder, see fit and eval metrics distributed results in hist object": [
            1,
            1
        ]
    },
    "metrics_centralized": {
        "accuracy": [
            [
                0,
                0.004
            ],
            [
                1,
                0.07733333333333334
            ],
            [
                2,
                0.308
            ],
            [
                3,
                0.2966666666666667
            ],
            [
                4,
                0.5253333333333333
            ],
            [
                5,
                0.6546666666666666
            ],
            [
                6,
                0.606
            ],
            [
                7,
                0.544
            ],
            [
                8,
                0.688
            ],
            [
                9,
                0.7026666666666667
            ],
            [
                10,
                0.688
            ]
        ]
    }
}